makinas/__init__.py
makinas/cli.py
makinas/client.py
makinas-0.0.3.dist-info/LICENSE
makinas-0.0.3.dist-info/METADATA
makinas-0.0.3.dist-info/WHEEL
makinas-0.0.3.dist-info/entry_points.txt
makinas-0.0.3.dist-info/top_level.txt
makinas-0.0.3.dist-info/RECORD
