Metadata-Version: 2.1
Name: makinas
Version: 0.0.3
Summary: Package for interfacing with Makinas APIs
Home-page: https://gitlab.com/makinas-nbt/pymakinas.git
Author: Nemanja Nikodijevic
Author-email: nemanja.nikodijevic@nbt.ag
License: UNKNOWN
Platform: UNKNOWN
Classifier: Programming Language :: Python :: 3
Classifier: License :: OSI Approved :: MIT License
Classifier: Operating System :: OS Independent
Requires-Python: >=3.5
Requires-Dist: requests (>=2.22.0)
Requires-Dist: tqdm (>=4.41.1)
